hajkr_youtube_scraper/__init__.py
hajkr_youtube_scraper/__main__.py
hajkr_youtube_scraper/crawler.py
hajkr_youtube_scraper/utils.py
hajkr_hajkr_youtube_scraper-0.0.3.dist-info/METADATA
hajkr_hajkr_youtube_scraper-0.0.3.dist-info/WHEEL
hajkr_hajkr_youtube_scraper-0.0.3.dist-info/top_level.txt
hajkr_hajkr_youtube_scraper-0.0.3.dist-info/RECORD
