Metadata-Version: 2.1
Name: hajkr-hajkr-youtube-scraper
Version: 0.0.3
Summary: A package for scraping youtube
Home-page: https://github.com/hajkr/youtube-scraper
Author: Tadej Hribar
Author-email: tadej.996@gmail.com
License: UNKNOWN
Platform: UNKNOWN
